README.txt
setup.py
src/tha/__init__.py
src/tha.coverage.egg-info/PKG-INFO
src/tha.coverage.egg-info/SOURCES.txt
src/tha.coverage.egg-info/dependency_links.txt
src/tha.coverage.egg-info/entry_points.txt
src/tha.coverage.egg-info/namespace_packages.txt
src/tha.coverage.egg-info/not-zip-safe
src/tha.coverage.egg-info/requires.txt
src/tha.coverage.egg-info/top_level.txt
src/tha/coverage/__init__.py
src/tha/coverage/script.py
src/tha/coverage/tests/__init__.py
src/tha/coverage/tests/test.py