Metadata-Version: 1.0
Name: tha.coverage
Version: 1.0.1-renamed-to-createcoverage
Summary: Provides single script to create coverage reports
Home-page: http://pypi.python.org/pypi/createzopecoverage
Author: Reinout van Rees
Author-email: reinout@vanrees.org
License: BSD
Platform: UNKNOWN
